{
    "language": "Kinyarwanda",
    "content": "Rwiyamwa ziga ingaga\nN'umugambi w'ihangu\nRwa ngoboka ya rugina\nIngeri ibanza mu rubuga\nItwara rukikampiri\n\nIcumu ryo mu ruti rw'indekwe\nRwavuye i Rusheshe\nRwiharaze isharankima.\nRwabaye igishami\nRugasagamba mu ijuri\n\nUburyo rwagabye amashami\nAho ruri ni se w'ishyamba\nKandi reka irukunde\nRubamo icumu ryiza\nYarigize umutabazi\n\nIntambara ntiruyita si\nKurya iruhoza mu rugina\nImbuga yarwo iratukura\nNtirukunda gutaha\nRutagwije imitumbi\n\nYarukubitiye umucuzi\nWakwemerana na rwo\nNgo arukatire icyuma\nRwabimbuye imihigo.\nImpuruza ikineshereza\n\nRwamuje mu nziza\nAri ukwiharira inzigo\nAbenshi baragiye Itiro\nRubajyanaho impamba\nAho rugeze ku mpama\n\nRucinyaho impayamaguru\nY'umushumba wa Mporera\nZa mpaka zirakuka\nYaruteye amaramu\nMuri bene Murenzi\n\nRubahina umurumango\nIgomba kurwunamura\nYanga ko rwaturika.\nYarukinduje umugabo\nUturuka mu Ruhitambazi\n\nAcyikanga igitutu\nImbuga yaryo iratebera\nAbura ubuhamagara abe\nAbura umurasira na rimwe\nRwa ruti rumuhirika aho\n\nIngeri zigicura inkumbi\nYarujyanye mu mbuga\nKurumanza amacibiri\nInkubirane iba iya kabiri\nMu kurembera umuroha\n\nYabakuye imirambi\nN'iyo ibagiriye isoni\nBirirwa bayisenga\nIbuhirira nimunsi\nAri ko bahangaza.\n\nNi uko inkuba zitegeka\nAbandi baragira inka mbi\nIngeri zirasuzugura\nNtibazabona izirimo\nIngoro y'umwogabyano!",
    "tags": [
        "Inka"
    ],
    "createdTime": "2021-10-19 13:33:30.792000+00:00",
    "id": "Qsyt3RJil35GNpu3zIkF",
    "source": "",
    "rating": 1.8649883733492152,
    "visibility": "public",
    "title": "Ingoro y'umwogabyano 7",
    "author": ""
}