{
    "language": "Kinyarwanda",
    "content": "Igituma bandirimba mu bihugu byose\nNgira ibirindiro bishyika ku ijana\nAbazi kubara barahanshinga.\nHari uwo niciye mu Ishishi no mu Bushora na Cyimbu\nNo mu Ruvugangoma rwa Musekera\n\nN'icyuma navugirije kuri Cyinuma.\nNiciye i Rubona rwa Tunda\nNtamirije umuheha mu ruhanga rw'inyambo.\nNiciye ku Rutambabarenzi rwa Kidaturwa\nNtamirije uko ntamirije uku.\n\nNica Bisangwahabona mu Mushya wa Murori\nMporera Nubaha akibona.\nNica Rutuku ku Ihenda anyihamagariye.\nNiciye mu ritagendwa rya Ngiga\nNdyivugiyemo rihinduka ibirori gusa!",
    "tags": [
        "Ibyivugo"
    ],
    "createdTime": "2021-10-19 13:33:23.502000+00:00",
    "id": "REBzvWHxNpEDNXNdItQD",
    "source": "",
    "rating": 54.4683495489681,
    "visibility": "public",
    "title": "Igituma bandirimba",
    "author": ""
}